fds/__init__.py
fds/sdk/__init__.py
fds/sdk/FactSetETF/__init__.py
fds/sdk/FactSetETF/api_client.py
fds/sdk/FactSetETF/configuration.py
fds/sdk/FactSetETF/exceptions.py
fds/sdk/FactSetETF/model_utils.py
fds/sdk/FactSetETF/rest.py
fds/sdk/FactSetETF/api/__init__.py
fds/sdk/FactSetETF/api/data_items_api.py
fds/sdk/FactSetETF/api/reference_api.py
fds/sdk/FactSetETF/apis/__init__.py
fds/sdk/FactSetETF/model/__init__.py
fds/sdk/FactSetETF/model/categories.py
fds/sdk/FactSetETF/model/category.py
fds/sdk/FactSetETF/model/error_response.py
fds/sdk/FactSetETF/model/error_response_sub_errors.py
fds/sdk/FactSetETF/model/etf_reference_data.py
fds/sdk/FactSetETF/model/etf_reference_data_request.py
fds/sdk/FactSetETF/model/etf_reference_data_response.py
fds/sdk/FactSetETF/model/ids.py
fds/sdk/FactSetETF/model/metric.py
fds/sdk/FactSetETF/model/metrics.py
fds/sdk/FactSetETF/model/metrics_response.py
fds/sdk/FactSetETF/models/__init__.py
fds.sdk.FactSetETF-1.0.13.dist-info/LICENSE
fds.sdk.FactSetETF-1.0.13.dist-info/METADATA
fds.sdk.FactSetETF-1.0.13.dist-info/WHEEL
fds.sdk.FactSetETF-1.0.13.dist-info/top_level.txt
fds.sdk.FactSetETF-1.0.13.dist-info/RECORD
